dkp/__init__.py
dkp/__main__.py
dkp/dkp.py
dkp/header.sh
dkp/restore.sh
dkp-0.2.0.dist-info/entry_points.txt
dkp-0.2.0.dist-info/LICENSE
dkp-0.2.0.dist-info/WHEEL
dkp-0.2.0.dist-info/METADATA
dkp-0.2.0.dist-info/RECORD
