Metadata-Version: 2.1
Name: dkp
Version: 0.2.0
Summary: DocKer compose Packer
License: MIT
Author: Aleksandr Baryshnikov
Author-email: owner@reddec.net
Requires-Python: >=3.8
Classifier: License :: OSI Approved :: MIT License
Classifier: Programming Language :: Python :: 3
Classifier: Programming Language :: Python :: 3.10
Classifier: Programming Language :: Python :: 3.8
Classifier: Programming Language :: Python :: 3.9
